[
    {
        "time": "04-08 20:33",
        "title": "邓肯比科比更伟大的3大理由！美媒指出关键一点，他是乔丹后最佳",
        "link": "https://new.qq.com/sv1/qd/aoyou.html?cmsid=20200408A0R7OH00",
        "images": [
            "https://inews.gtimg.com/newsapp_ls/0/11556141593_295195/0",
            "https://inews.gtimg.com/newsapp_ls/0/11556141594_295195/0",
            "https://inews.gtimg.com/newsapp_ls/0/11556141595_295195/0"
        ]
    },
    {
        "time": "04-08 06:37",
        "title": "合同年遇见缩水季3人欢喜3人忧？快船留双魔兽或怒省千万",
        "link": "https://new.qq.com/sv1/qd/aoyou.html?cmsid=20200403A0M5AL00",
        "images": [
            "https://inews.gtimg.com/newsapp_ls/0/11552430725_295195/0",
            "https://inews.gtimg.com/newsapp_ls/0/11552430726_295195/0",
            "https://inews.gtimg.com/newsapp_ls/0/11552430727_295195/0"
        ]
    },
    {
        "time": "04-07 14:00",
        "title": "NCAA决赛十大时刻：魔术师与伯德交手 2016经典绝杀与反绝杀",
        "link": "https://new.qq.com/sv1/qd/aoyou.html?cmsid=NBA2020040701036300",
        "images": [
            "https://inews.gtimg.com/newsapp_ls/0/11549162725_294195/0"
        ]
    },
    {
        "time": "04-07 12:23",
        "title": "NBA经典战“疫”回放：霍里压哨三分绝杀 湖人西决完成24分逆转",
        "link": "https://new.qq.com/sv1/qd/aoyou.html?cmsid=NBA2020040700888500",
        "images": [
            "https://inews.gtimg.com/newsapp_ls/0/11548795647_294195/0"
        ]
    },
    {
        "time": "04-09 10:25",
        "title": "NBA若取消，这10名球员或损失最大！詹姆斯退还850万列第二",
        "link": "https://new.qq.com/sv1/qd/aoyou.html?cmsid=20200409A077J900",
        "images": [
            "https://inews.gtimg.com/newsapp_ls/0/11558204796_295195/0",
            "https://inews.gtimg.com/newsapp_ls/0/11558204797_295195/0",
            "https://inews.gtimg.com/newsapp_ls/0/11558204798_295195/0"
        ]
    },
    {
        "time": "04-09 08:59",
        "title": "里弗斯曝小卡和乔治停赛期保持高强度训练 曾预感快船将迎来一波连胜",
        "link": "https://new.qq.com/sv1/qd/aoyou.html?cmsid=20200409A04OC500",
        "images": [
            "https://inews.gtimg.com/newsapp_ls/0/11557813189_294195/0"
        ]
    },
    {
        "time": "04-09 07:36",
        "title": "美媒建议湖人交易保罗 詹眉组合升级三巨头？交易最大难点在哪里",
        "link": "https://new.qq.com/sv1/qd/aoyou.html?cmsid=20200409A02ZN800",
        "images": [
            "https://inews.gtimg.com/newsapp_ls/0/11557589496_295195/0",
            "https://inews.gtimg.com/newsapp_ls/0/11557589497_295195/0",
            "https://inews.gtimg.com/newsapp_ls/0/11557589498_295195/0"
        ]
    },
    {
        "time": "04-09 07:51",
        "title": "美球迷票选第一强队！十六队PK结果揭晓，17勇士难敌96公牛",
        "link": "https://new.qq.com/sv1/qd/aoyou.html?cmsid=20200409A03M1S00",
        "images": [
            "https://inews.gtimg.com/newsapp_ls/0/11557615144_294195/0",
            "https://inews.gtimg.com/newsapp_ls/0/11557615383_294195/0",
            "https://inews.gtimg.com/newsapp_ls/0/11557615623_294195/0"
        ]
    },
    {
        "time": "04-09 08:43",
        "title": "畅销书排行榜第一！科比新作获热捧，瓦妮莎致谢：曼巴再次出击",
        "link": "https://new.qq.com/sv1/qd/aoyou.html?cmsid=20200409A04DXI00",
        "images": [
            "https://inews.gtimg.com/newsapp_ls/0/11557761147_295195/0",
            "https://inews.gtimg.com/newsapp_ls/0/11557761148_295195/0",
            "https://inews.gtimg.com/newsapp_ls/0/11557761149_295195/0"
        ]
    },
    {
        "time": "04-09 10:07",
        "title": "恒大国安机会来了！可从西班牙人引进中国第一前锋，签约条件曝光",
        "link": "https://new.qq.com/sv1/qd/aoyou.html?cmsid=20200409A06KYI00",
        "images": [
            "https://inews.gtimg.com/newsapp_ls/0/11558108161_295195/0",
            "https://inews.gtimg.com/newsapp_ls/0/11558108162_295195/0",
            "https://inews.gtimg.com/newsapp_ls/0/11558108163_295195/0"
        ]
    },
    {
        "time": "04-09 06:59",
        "title": "曝湖人仍想打造三巨头！保罗成潜在选择，出色一季让他变香饽饽？",
        "link": "https://new.qq.com/sv1/qd/aoyou.html?cmsid=20200409A0313B00",
        "images": [
            "https://inews.gtimg.com/newsapp_ls/0/11557512983_295195/0",
            "https://inews.gtimg.com/newsapp_ls/0/11557512985_295195/0",
            "https://inews.gtimg.com/newsapp_ls/0/11557512986_295195/0"
        ]
    },
    {
        "time": "04-09 08:00",
        "title": "揭皇马降薪谈判内幕：6天达成协议，拉莫斯齐达内带头支持老佛爷",
        "link": "https://new.qq.com/sv1/qd/aoyou.html?cmsid=20200409A03P6N00",
        "images": [
            "https://inews.gtimg.com/newsapp_ls/0/11557636500_294195/0"
        ]
    },
    {
        "time": "04-09 09:09",
        "title": "杜德利：浓眉哥领袖角色被低估 他有时比詹姆斯更有话语权",
        "link": "https://new.qq.com/sv1/qd/aoyou.html?cmsid=20200409A04Y8300",
        "images": [
            "https://inews.gtimg.com/newsapp_ls/0/11557857312_294195/0"
        ]
    },
    {
        "time": "04-09 10:06",
        "title": "并非世界纪录之战！外国网友评博尔特生涯经典比赛 北京奥运成榜首",
        "link": "https://new.qq.com/sv1/qd/aoyou.html?cmsid=20200409A06F8Z00",
        "images": [
            "https://inews.gtimg.com/newsapp_ls/0/11558074831_295195/0",
            "https://inews.gtimg.com/newsapp_ls/0/11558074832_295195/0",
            "https://inews.gtimg.com/newsapp_ls/0/11558074833_295195/0"
        ]
    },
    {
        "time": "04-09 08:16",
        "title": "乔丹前队友：奇才时期失去对他的敬意 明明我更好非要围绕他打",
        "link": "https://new.qq.com/sv1/qd/aoyou.html?cmsid=20200409A03YS100",
        "images": [
            "https://inews.gtimg.com/newsapp_ls/0/11557687088_294195/0"
        ]
    },
    {
        "time": "04-09 08:45",
        "title": "科比新书成美国最畅销书首位！瓦妮莎：丈夫若能看到应该会很骄傲",
        "link": "https://new.qq.com/sv1/qd/aoyou.html?cmsid=20200409A04EZC00",
        "images": [
            "https://inews.gtimg.com/newsapp_ls/0/11557767527_295195/0",
            "https://inews.gtimg.com/newsapp_ls/0/11557767528_295195/0",
            "https://inews.gtimg.com/newsapp_ls/0/11557767530_295195/0"
        ]
    },
    {
        "time": "04-09 09:29",
        "title": "好消息！国际足联给中国足协开绿灯，球迷：中超要成世界第一联赛",
        "link": "https://new.qq.com/sv1/qd/aoyou.html?cmsid=20200409A05GGO00",
        "images": [
            "https://inews.gtimg.com/newsapp_ls/0/11557931342_295195/0",
            "https://inews.gtimg.com/newsapp_ls/0/11557931343_295195/0",
            "https://inews.gtimg.com/newsapp_ls/0/11557931344_295195/0"
        ]
    },
    {
        "time": "04-09 10:08",
        "title": "美国死亡超1.4万，川建国称控制在10万内就成功，詹姆斯感到绝望",
        "link": "https://new.qq.com/sv1/qd/aoyou.html?cmsid=20200409A06P7J00",
        "images": [
            "https://inews.gtimg.com/newsapp_ls/0/11558097477_294195/0",
            "https://inews.gtimg.com/newsapp_ls/0/11558097474_294195/0",
            "https://inews.gtimg.com/newsapp_ls/0/11558098487_294195/0"
        ]
    },
    {
        "time": "04-09 08:30",
        "title": "詹皇坦言若本赛季取消，自己会神伤！名嘴曾说本季是老詹最后夺冠机会",
        "link": "https://new.qq.com/sv1/qd/aoyou.html?cmsid=20200409A0451S00",
        "images": [
            "https://inews.gtimg.com/newsapp_ls/0/11557721460_295195/0",
            "https://inews.gtimg.com/newsapp_ls/0/11557721461_295195/0",
            "https://inews.gtimg.com/newsapp_ls/0/11557721462_295195/0"
        ]
    },
    {
        "time": "04-09 09:41",
        "title": "前NBA记者爆料！加内特人品很差还耍大牌 杨毅：和他共事太不容易",
        "link": "https://new.qq.com/sv1/qd/aoyou.html?cmsid=20200409A05UP400",
        "images": [
            "https://inews.gtimg.com/newsapp_ls/0/11557986793_295195/0",
            "https://inews.gtimg.com/newsapp_ls/0/11557986794_295195/0",
            "https://inews.gtimg.com/newsapp_ls/0/11557986795_295195/0"
        ]
    },
    {
        "time": "04-09 08:40",
        "title": "科尔称16-17赛季骑士最强 詹姆斯那年丢冠 是因为勇士有杜兰特",
        "link": "https://new.qq.com/sv1/qd/aoyou.html?cmsid=20200409A04C0S00",
        "images": [
            "https://inews.gtimg.com/newsapp_ls/0/11557753885_295195/0",
            "https://inews.gtimg.com/newsapp_ls/0/11557753886_295195/0",
            "https://inews.gtimg.com/newsapp_ls/0/11557753887_295195/0"
        ]
    },
    {
        "time": "04-09 08:49",
        "title": "很不甘心，詹姆斯：不能打完这个赛季，找不到任何的宽慰",
        "link": "https://new.qq.com/sv1/qd/aoyou.html?cmsid=20200409A04HSY00",
        "images": [
            "https://inews.gtimg.com/newsapp_ls/0/11557781158_295195/0",
            "https://inews.gtimg.com/newsapp_ls/0/11557781159_295195/0",
            "https://inews.gtimg.com/newsapp_ls/0/11557781160_295195/0"
        ]
    },
    {
        "time": "04-09 08:53",
        "title": "猫神真有可能退隐了？凌晨1点发文“想休息了”，Alan的回复引人遐想！",
        "link": "https://new.qq.com/sv1/qd/aoyou.html?cmsid=20200409A04KAB00",
        "images": [
            "https://inews.gtimg.com/newsapp_ls/0/11557798651_295195/0",
            "https://inews.gtimg.com/newsapp_ls/0/11557798652_295195/0",
            "https://inews.gtimg.com/newsapp_ls/0/11557798653_295195/0"
        ]
    },
    {
        "time": "04-09 08:25",
        "title": "麦科勒姆：很多球员都是“月光族” 这么说并非装可怜",
        "link": "https://new.qq.com/sv1/qd/aoyou.html?cmsid=20200409A042XU00",
        "images": [
            "https://inews.gtimg.com/newsapp_ls/0/11557709002_294195/0"
        ]
    },
    {
        "time": "04-09 10:00",
        "title": "欧洲足坛酝酿巨变！意甲第3锁定两大目标：签下梅西＋拿欧冠冠军！",
        "link": "https://new.qq.com/sv1/qd/aoyou.html?cmsid=20200409A06DXC00",
        "images": [
            "https://inews.gtimg.com/newsapp_ls/0/11558064382_295195/0",
            "https://inews.gtimg.com/newsapp_ls/0/11558064383_295195/0",
            "https://inews.gtimg.com/newsapp_ls/0/11558064384_295195/0"
        ]
    },
    {
        "time": "04-09 10:01",
        "title": "科比新书成美国最畅销书首位！瓦妮莎：丈夫若能看到应该会很骄傲",
        "link": "https://new.qq.com/sv1/qd/aoyou.html?cmsid=SPO2020040900523300",
        "images": [
            "https://inews.gtimg.com/newsapp_ls/0/11558045982_294195/0"
        ]
    },
    {
        "time": "04-09 08:31",
        "title": "如果奥登不遭重伤打击会怎样？或将超越海军上将成为超一流中锋",
        "link": "https://new.qq.com/sv1/qd/aoyou.html?cmsid=20200409A0460S00",
        "images": [
            "https://inews.gtimg.com/newsapp_ls/0/11557726948_295195/0",
            "https://inews.gtimg.com/newsapp_ls/0/11557726949_295195/0",
            "https://inews.gtimg.com/newsapp_ls/0/11557726952_295195/0"
        ]
    },
    {
        "time": "04-09 08:47",
        "title": "马内：我能接受利物浦本赛季无冠 希望明年冠军还是我们的",
        "link": "https://new.qq.com/sv1/qd/aoyou.html?cmsid=20200409A04GHE00",
        "images": [
            "https://inews.gtimg.com/newsapp_ls/0/11557774415_294195/0"
        ]
    },
    {
        "time": "04-09 09:28",
        "title": "克雷斯波：大罗无人能及，摆脱后卫的能力无可比拟 C罗创造力不够",
        "link": "https://new.qq.com/sv1/qd/aoyou.html?cmsid=20200409A05GNC00",
        "images": [
            "https://inews.gtimg.com/newsapp_ls/0/11557926677_295195/0",
            "https://inews.gtimg.com/newsapp_ls/0/11557926679_295195/0",
            "https://inews.gtimg.com/newsapp_ls/0/11557926680_295195/0"
        ]
    },
    {
        "time": "04-09 09:43",
        "title": "勇士队谁最像乔丹？科尔答案出人意料 称格林和乔丹有1共同点",
        "link": "https://new.qq.com/sv1/qd/aoyou.html?cmsid=20200409A05VY600",
        "images": [
            "https://inews.gtimg.com/newsapp_ls/0/11557991104_295195/0",
            "https://inews.gtimg.com/newsapp_ls/0/11557991105_295195/0",
            "https://inews.gtimg.com/newsapp_ls/0/11557991106_295195/0"
        ]
    },
    {
        "time": "04-09 08:32",
        "title": "35岁詹皇的真实想法，想带领湖人夺冠，表态：不复赛就无法宽慰",
        "link": "https://new.qq.com/sv1/qd/aoyou.html?cmsid=20200409A046B200",
        "images": [
            "https://inews.gtimg.com/newsapp_ls/0/11557729325_295195/0",
            "https://inews.gtimg.com/newsapp_ls/0/11557729326_295195/0",
            "https://inews.gtimg.com/newsapp_ls/0/11557729327_295195/0"
        ]
    },
    {
        "time": "04-09 07:42",
        "title": "西甲任意球之王！梅西过去10年打入33粒任意球，超C罗一倍！",
        "link": "https://new.qq.com/sv1/qd/aoyou.html?cmsid=20200409A03J7400",
        "images": [
            "https://inews.gtimg.com/newsapp_ls/0/11557603039_295195/0",
            "https://inews.gtimg.com/newsapp_ls/0/11557603040_295195/0",
            "https://inews.gtimg.com/newsapp_ls/0/11557603041_295195/0"
        ]
    },
    {
        "time": "04-09 08:00",
        "title": "专家问答：别再追问湖人谁确诊了 医患信息保密是最基本的道德底线",
        "link": "https://new.qq.com/sv1/qd/aoyou.html?cmsid=20200408A0S0EW00",
        "images": [
            "https://inews.gtimg.com/newsapp_ls/0/11557640546_295195/0",
            "https://inews.gtimg.com/newsapp_ls/0/11557640547_295195/0",
            "https://inews.gtimg.com/newsapp_ls/0/11557640549_295195/0"
        ]
    },
    {
        "time": "04-09 09:50",
        "title": "恭喜郎平！女排两大球星强势崛起，携朱婷缔造佳话",
        "link": "https://new.qq.com/sv1/qd/aoyou.html?cmsid=20200409A0620800",
        "images": [
            "https://inews.gtimg.com/newsapp_ls/0/11558041017_295195/0",
            "https://inews.gtimg.com/newsapp_ls/0/11558041018_295195/0",
            "https://inews.gtimg.com/newsapp_ls/0/11558041020_295195/0"
        ]
    },
    {
        "time": "04-09 09:42",
        "title": "湖人3换1造3巨头？夏季攻略曝光，保罗或联手詹皇弥补9年之憾",
        "link": "https://new.qq.com/sv1/qd/aoyou.html?cmsid=20200409A05VJJ00",
        "images": [
            "https://inews.gtimg.com/newsapp_ls/0/11557988103_295195/0",
            "https://inews.gtimg.com/newsapp_ls/0/11557988104_295195/0",
            "https://inews.gtimg.com/newsapp_ls/0/11557988105_295195/0"
        ]
    },
    {
        "time": "04-09 07:57",
        "title": "塔图姆评现役最强阵容：湖人两将强势入围 库里是联盟第一控卫",
        "link": "https://new.qq.com/sv1/qd/aoyou.html?cmsid=20200409A03NXF00",
        "images": [
            "https://inews.gtimg.com/newsapp_ls/0/11557630165_295195/0",
            "https://inews.gtimg.com/newsapp_ls/0/11557630166_295195/0",
            "https://inews.gtimg.com/newsapp_ls/0/11557630167_295195/0"
        ]
    },
    {
        "time": "04-09 08:19",
        "title": "《疯狂的篮球第九期》小卡敌我不分神卧底领衔快船下饭集锦",
        "link": "https://new.qq.com/sv1/qd/aoyou.html?cmsid=SPO2020040900303500",
        "images": [
            "https://inews.gtimg.com/newsapp_ls/0/11557691571_294195/0"
        ]
    },
    {
        "time": "04-09 08:37",
        "title": "再见胡尔克，上港将失去球队大腿，土超豪门或成最大赢家！",
        "link": "https://new.qq.com/sv1/qd/aoyou.html?cmsid=20200409A04AIC00",
        "images": [
            "https://inews.gtimg.com/newsapp_ls/0/11557746842_295195/0",
            "https://inews.gtimg.com/newsapp_ls/0/11557746843_295195/0",
            "https://inews.gtimg.com/newsapp_ls/0/11557746844_295195/0"
        ]
    },
    {
        "time": "04-09 08:30",
        "title": "2003年选秀大会重排：詹姆斯韦德领衔，第18顺位内线逆袭前五",
        "link": "https://new.qq.com/sv1/qd/aoyou.html?cmsid=20200409A0440F00",
        "images": [
            "https://inews.gtimg.com/newsapp_ls/0/11557725443_295195/0",
            "https://inews.gtimg.com/newsapp_ls/0/11557725444_295195/0",
            "https://inews.gtimg.com/newsapp_ls/0/11557725446_295195/0"
        ]
    },
    {
        "time": "04-09 07:47",
        "title": "加内特：科比离世之后 2020年成了多事之秋",
        "link": "https://new.qq.com/sv1/qd/aoyou.html?cmsid=20200409A03KU900",
        "images": [
            "https://inews.gtimg.com/newsapp_ls/0/11557612981_294195/0"
        ]
    },
    {
        "time": "04-09 07:22",
        "title": "中韩名将重拳对攻 张立鹏冲上去砸击锁脖子击败强敌",
        "link": "https://new.qq.com/sv1/qd/aoyou.html?cmsid=SPO2020040900163100",
        "images": [
            "https://inews.gtimg.com/newsapp_ls/0/11557542606_294195/0"
        ]
    },
    {
        "time": "04-09 08:39",
        "title": "詹姆斯盼NBA重启？中国球迷：中超＋CBA都遥遥无期，更别提NBA了",
        "link": "https://new.qq.com/sv1/qd/aoyou.html?cmsid=20200409A04BAR00",
        "images": [
            "https://inews.gtimg.com/newsapp_ls/0/11557749612_295195/0",
            "https://inews.gtimg.com/newsapp_ls/0/11557749613_295195/0",
            "https://inews.gtimg.com/newsapp_ls/0/11557749614_295195/0"
        ]
    },
    {
        "time": "04-09 08:10",
        "title": "提起足坛战神，80后球迷心中只会浮现他的名字……",
        "link": "https://new.qq.com/sv1/qd/aoyou.html?cmsid=20200409A03YF600",
        "images": [
            "https://inews.gtimg.com/newsapp_ls/0/11557685567_295195/0",
            "https://inews.gtimg.com/newsapp_ls/0/11557685568_295195/0",
            "https://inews.gtimg.com/newsapp_ls/0/11557685569_295195/0"
        ]
    },
    {
        "time": "04-09 09:02",
        "title": "皇马比巴萨厚道？赛季取消才降薪20％！巴萨为何就直降70％？",
        "link": "https://new.qq.com/sv1/qd/aoyou.html?cmsid=20200409A04QD000",
        "images": [
            "https://inews.gtimg.com/newsapp_ls/0/11557821045_295195/0",
            "https://inews.gtimg.com/newsapp_ls/0/11557821047_295195/0",
            "https://inews.gtimg.com/newsapp_ls/0/11557821048_295195/0"
        ]
    },
    {
        "time": "04-09 07:18",
        "title": "32岁乐福不收拾骑士3巨头时代烂摊子 再追三年梦不香吗？",
        "link": "https://new.qq.com/sv1/qd/aoyou.html?cmsid=20200406A071EX00",
        "images": [
            "https://inews.gtimg.com/newsapp_ls/0/11557567191_295195/0",
            "https://inews.gtimg.com/newsapp_ls/0/11557567192_295195/0",
            "https://inews.gtimg.com/newsapp_ls/0/11557567194_295195/0"
        ]
    },
    {
        "time": "04-09 10:01",
        "title": "天啊噜！这还是高拉特吗？隔离期间卖力训练，腹肌抢眼汗流浃背",
        "link": "https://new.qq.com/sv1/qd/aoyou.html?cmsid=20200409V06B3300",
        "images": [
            "https://inews.gtimg.com/newsapp_ls/0/11558055354_294195/0"
        ]
    },
    {
        "time": "04-09 10:16",
        "title": "程咬金每款皮肤代表一个身份，穷人自带嘲讽，大神都用他",
        "link": "https://new.qq.com/sv1/qd/aoyou.html?cmsid=20200408A0MXTT00",
        "images": [
            "https://inews.gtimg.com/newsapp_ls/0/11558143635_295195/0",
            "https://inews.gtimg.com/newsapp_ls/0/11558143636_295195/0",
            "https://inews.gtimg.com/newsapp_ls/0/11558143637_295195/0"
        ]
    },
    {
        "time": "04-09 10:04",
        "title": "科比、邓肯与加内特，谁拥有更好的球鞋生涯？",
        "link": "https://new.qq.com/sv1/qd/aoyou.html?cmsid=20200409A06JF200",
        "images": [
            "https://inews.gtimg.com/newsapp_ls/0/11558089174_295195/0",
            "https://inews.gtimg.com/newsapp_ls/0/11558089175_295195/0",
            "https://inews.gtimg.com/newsapp_ls/0/11558089176_295195/0"
        ]
    },
    {
        "time": "04-09 10:04",
        "title": "ES经理向LPL道歉，再也不会侮辱LPL，PDD：要永远保持谦卑的心",
        "link": "https://new.qq.com/sv1/qd/aoyou.html?cmsid=20200409A06J8800",
        "images": [
            "https://inews.gtimg.com/newsapp_ls/0/11558076964_294195/0",
            "https://inews.gtimg.com/newsapp_ls/0/11558076970_294195/0",
            "https://inews.gtimg.com/newsapp_ls/0/11558076975_294195/0"
        ]
    },
    {
        "time": "04-09 08:36",
        "title": "38岁韩寒跑5公里仅用18分钟，如此配速堪称业余圈“跑神”",
        "link": "https://new.qq.com/sv1/qd/aoyou.html?cmsid=20200409A049LW00",
        "images": [
            "https://inews.gtimg.com/newsapp_ls/0/11557737103_294195/0",
            "https://inews.gtimg.com/newsapp_ls/0/11557737102_294195/0",
            "https://inews.gtimg.com/newsapp_ls/0/11557737105_294195/0"
        ]
    },
    {
        "time": "04-09 07:46",
        "title": "吹爆恒大！7年前一战制霸亚洲，艾克森两球封神，中超从未这么嗨",
        "link": "https://new.qq.com/sv1/qd/aoyou.html?cmsid=20200409A03KH900",
        "images": [
            "https://inews.gtimg.com/newsapp_ls/0/11557611019_295195/0",
            "https://inews.gtimg.com/newsapp_ls/0/11557611020_295195/0",
            "https://inews.gtimg.com/newsapp_ls/0/11557611021_295195/0"
        ]
    },
    {
        "time": "04-09 08:35",
        "title": "队长力劝桑乔不要去曼联：再沉淀1-2年，没有比多特更好的地方",
        "link": "https://new.qq.com/sv1/qd/aoyou.html?cmsid=20200409A048QQ00",
        "images": [
            "https://inews.gtimg.com/newsapp_ls/0/11557742917_295195/0",
            "https://inews.gtimg.com/newsapp_ls/0/11557742918_295195/0",
            "https://inews.gtimg.com/newsapp_ls/0/11557742919_295195/0"
        ]
    },
    {
        "time": "04-09 08:58",
        "title": "詹皇停赛期间会和主帅保持联系 针对NBA复赛：安全健康才是最重要",
        "link": "https://new.qq.com/sv1/qd/aoyou.html?cmsid=20200409A04N6700",
        "images": [
            "https://inews.gtimg.com/newsapp_ls/0/11557802720_294195/0",
            "https://inews.gtimg.com/newsapp_ls/0/11557802746_294195/0",
            "https://inews.gtimg.com/newsapp_ls/0/11557802742_294195/0"
        ]
    },
    {
        "time": "04-09 08:15",
        "title": "契约精神？桑切斯拒不降薪拒不离队，宁可无球可踢也要熬完合同",
        "link": "https://new.qq.com/sv1/qd/aoyou.html?cmsid=20200409A03VIS00",
        "images": [
            "https://inews.gtimg.com/newsapp_ls/0/11557685704_295195/0",
            "https://inews.gtimg.com/newsapp_ls/0/11557685705_295195/0",
            "https://inews.gtimg.com/newsapp_ls/0/11557685706_295195/0"
        ]
    },
    {
        "time": "04-09 09:27",
        "title": "新疆男篮恐现神操作！西热招募北京天才吴勇豪，球迷：捡漏上瘾？",
        "link": "https://new.qq.com/sv1/qd/aoyou.html?cmsid=20200409A05FIF00",
        "images": [
            "https://inews.gtimg.com/newsapp_ls/0/11557913663_294195/0",
            "https://inews.gtimg.com/newsapp_ls/0/11557913661_294195/0",
            "https://inews.gtimg.com/newsapp_ls/0/11557913662_294195/0"
        ]
    },
    {
        "time": "04-09 09:18",
        "title": "天海准入突然停滞！又出问题了，这次可别怪足协",
        "link": "https://new.qq.com/sv1/qd/aoyou.html?cmsid=20200409A055II00",
        "images": [
            "https://inews.gtimg.com/newsapp_ls/0/11557888873_294195/0"
        ]
    },
    {
        "time": "04-09 09:06",
        "title": "切尔西与巴萨达成协议，库蒂尼奥将租借加盟",
        "link": "https://new.qq.com/sv1/qd/aoyou.html?cmsid=20200409A04W9L00",
        "images": [
            "https://inews.gtimg.com/newsapp_ls/0/11557841459_294195/0"
        ]
    },
    {
        "time": "04-09 09:14",
        "title": "身价暴跌！皇马新7号8个月贬值7000万欧，赛季仅打入1球",
        "link": "https://new.qq.com/sv1/qd/aoyou.html?cmsid=20200409A053KZ00",
        "images": [
            "https://inews.gtimg.com/newsapp_ls/0/11557874086_295195/0",
            "https://inews.gtimg.com/newsapp_ls/0/11557874087_295195/0",
            "https://inews.gtimg.com/newsapp_ls/0/11557874088_295195/0"
        ]
    },
    {
        "time": "04-09 09:10",
        "title": "阿根廷名宿：C罗梅西互相成就但罗纳尔多无法企及，劳塔罗比阿圭罗更团队",
        "link": "https://new.qq.com/sv1/qd/aoyou.html?cmsid=20200409A04ZE900",
        "images": [
            "https://inews.gtimg.com/newsapp_ls/0/11557854087_294195/0"
        ]
    },
    {
        "time": "04-09 09:09",
        "title": "韦世豪如日中天！张修维刘奕鸣们还有机会，昔日国青主力却一筹莫展",
        "link": "https://new.qq.com/sv1/qd/aoyou.html?cmsid=20200409A04Y8700",
        "images": [
            "https://inews.gtimg.com/newsapp_ls/0/11557851784_295195/0",
            "https://inews.gtimg.com/newsapp_ls/0/11557851785_295195/0",
            "https://inews.gtimg.com/newsapp_ls/0/11557851786_295195/0"
        ]
    },
    {
        "time": "04-09 07:35",
        "title": "这也能扔进去？ 盘点NBA那些花式非常规姿势的进球",
        "link": "https://new.qq.com/sv1/qd/aoyou.html?cmsid=SPO2020040900204800",
        "images": [
            "https://inews.gtimg.com/newsapp_ls/0/11557581572_294195/0"
        ]
    },
    {
        "time": "04-09 08:28",
        "title": "超级转会启动？阿媒：国米已为签下梅西做好准备",
        "link": "https://new.qq.com/sv1/qd/aoyou.html?cmsid=20200409A046UU00",
        "images": [
            "https://inews.gtimg.com/newsapp_ls/0/11557729417_294195/0"
        ]
    },
    {
        "time": "04-09 08:15",
        "title": "张本平野伊藤入选！日本组奥运特战队 张本领特别津贴到中国密训",
        "link": "https://new.qq.com/sv1/qd/aoyou.html?cmsid=20200409A03YIK00",
        "images": [
            "https://inews.gtimg.com/newsapp_ls/0/11557686603_295195/0",
            "https://inews.gtimg.com/newsapp_ls/0/11557686604_295195/0",
            "https://inews.gtimg.com/newsapp_ls/0/11557686605_295195/0"
        ]
    },
    {
        "time": "04-09 08:51",
        "title": "温斯顿谈及被布雷迪抢首发：被史上最佳四分卫取代是我的荣幸",
        "link": "https://new.qq.com/sv1/qd/aoyou.html?cmsid=20200409A04J2H00",
        "images": [
            "https://inews.gtimg.com/newsapp_ls/0/11557787849_295195/0",
            "https://inews.gtimg.com/newsapp_ls/0/11557787850_295195/0",
            "https://inews.gtimg.com/newsapp_ls/0/11557787851_295195/0"
        ]
    },
    {
        "time": "04-09 08:40",
        "title": "他曾破米兰阿森纳大门，神之一手抽扑克拿亚军！谢峰54岁生日快乐",
        "link": "https://new.qq.com/sv1/qd/aoyou.html?cmsid=20200408A0UA2700",
        "images": [
            "https://inews.gtimg.com/newsapp_ls/0/11557753135_295195/0",
            "https://inews.gtimg.com/newsapp_ls/0/11557753136_295195/0",
            "https://inews.gtimg.com/newsapp_ls/0/11557753137_295195/0"
        ]
    },
    {
        "time": "04-09 08:05",
        "title": "尤文米兰酝酿交易，贝尔纳代斯基交换唐纳鲁马",
        "link": "https://new.qq.com/sv1/qd/aoyou.html?cmsid=20200409A03U9100",
        "images": [
            "https://inews.gtimg.com/newsapp_ls/0/11557660209_294195/0"
        ]
    },
    {
        "time": "04-09 07:34",
        "title": "千万就能留人？开拓者复兴在即 三枪＋双塔将成西部顶级阵容",
        "link": "https://new.qq.com/sv1/qd/aoyou.html?cmsid=20200403A0BERH00",
        "images": [
            "https://inews.gtimg.com/newsapp_ls/0/11557585131_295195/0",
            "https://inews.gtimg.com/newsapp_ls/0/11557585132_295195/0",
            "https://inews.gtimg.com/newsapp_ls/0/11557585133_295195/0"
        ]
    },
    {
        "time": "04-09 07:21",
        "title": "张伟丽100万不经花，乔安娜代言不断晒百万豪车，她要一直卫冕下去",
        "link": "https://new.qq.com/sv1/qd/aoyou.html?cmsid=20200409A03ACK00",
        "images": [
            "https://inews.gtimg.com/newsapp_ls/0/11557563079_295195/0",
            "https://inews.gtimg.com/newsapp_ls/0/11557563080_295195/0",
            "https://inews.gtimg.com/newsapp_ls/0/11557563081_295195/0"
        ]
    },
    {
        "time": "04-09 08:51",
        "title": "疫情之下足坛球员身价蒸发92亿欧 梅西市值已被20岁小将超越",
        "link": "https://new.qq.com/sv1/qd/aoyou.html?cmsid=20200409A04J1H00",
        "images": [
            "https://inews.gtimg.com/newsapp_ls/0/11557807943_294195/0"
        ]
    },
    {
        "time": "04-09 08:41",
        "title": "意媒：萨里对拉比奥和拉姆塞有信心，他们不会在夏季离开",
        "link": "https://new.qq.com/sv1/qd/aoyou.html?cmsid=20200409A04CH700",
        "images": [
            "https://inews.gtimg.com/newsapp_ls/0/11557754722_295195/0",
            "https://inews.gtimg.com/newsapp_ls/0/11557754723_295195/0",
            "https://inews.gtimg.com/newsapp_ls/0/11557754724_295195/0"
        ]
    },
    {
        "time": "04-09 06:35",
        "title": "这也许就是国足放弃李可的真正原因，球迷：比第六联赛更好笑！",
        "link": "https://new.qq.com/sv1/qd/aoyou.html?cmsid=20200409A00V6I00",
        "images": [
            "https://inews.gtimg.com/newsapp_ls/0/11557482642_295195/0",
            "https://inews.gtimg.com/newsapp_ls/0/11557482643_295195/0",
            "https://inews.gtimg.com/newsapp_ls/0/11557482644_295195/0"
        ]
    },
    {
        "time": "04-09 07:33",
        "title": "加时绝杀是何感觉？盘点NBA加时赛那些精彩绝杀",
        "link": "https://new.qq.com/sv1/qd/aoyou.html?cmsid=SPO2020040900203000",
        "images": [
            "https://inews.gtimg.com/newsapp_ls/0/11557579466_294195/0"
        ]
    },
    {
        "time": "04-09 07:26",
        "title": "他11年前被老板钦点世界冠军！3脚踢翻布洛克莱斯纳，还是高材生",
        "link": "https://new.qq.com/sv1/qd/aoyou.html?cmsid=20200408A0UIIP00",
        "images": [
            "https://inews.gtimg.com/newsapp_ls/0/11556889399_295195/0",
            "https://inews.gtimg.com/newsapp_ls/0/11556889400_295195/0",
            "https://inews.gtimg.com/newsapp_ls/0/11556889401_295195/0"
        ]
    },
    {
        "time": "04-09 07:30",
        "title": "奥尼尔爆巴克利上节目不穿内裤 看看巴克利如何爆笑回应",
        "link": "https://new.qq.com/sv1/qd/aoyou.html?cmsid=SPO2020040900197800",
        "images": [
            "https://inews.gtimg.com/newsapp_ls/0/11557572510_294195/0"
        ]
    },
    {
        "time": "04-09 07:43",
        "title": "克雷斯波：C罗梅西也难比大罗，劳塔罗强于阿圭罗",
        "link": "https://new.qq.com/sv1/qd/aoyou.html?cmsid=20200409A03KUE00",
        "images": [
            "https://inews.gtimg.com/newsapp_ls/0/11557612737_294195/0"
        ]
    },
    {
        "time": "04-09 07:40",
        "title": "全力詹模式开启！混剪回顾詹姆斯2018年3大超神绝杀",
        "link": "https://new.qq.com/sv1/qd/aoyou.html?cmsid=SPO2020040900219200",
        "images": [
            "https://inews.gtimg.com/newsapp_ls/0/11557594619_294195/0"
        ]
    },
    {
        "time": "04-09 07:26",
        "title": "传统武术和现代搏击到底是什么关系？邱建良的经历或能给出答案",
        "link": "https://new.qq.com/sv1/qd/aoyou.html?cmsid=20200408A0TCN600",
        "images": [
            "https://inews.gtimg.com/newsapp_ls/0/11556685971_295195/0",
            "https://inews.gtimg.com/newsapp_ls/0/11556685972_295195/0",
            "https://inews.gtimg.com/newsapp_ls/0/11556685973_295195/0"
        ]
    },
    {
        "time": "04-09 07:35",
        "title": "奥胖儿子：手机壁纸是和科比最后聊天截图 每天都激励着自己",
        "link": "https://new.qq.com/sv1/qd/aoyou.html?cmsid=20200409A03GKA00",
        "images": [
            "https://inews.gtimg.com/newsapp_ls/0/11557586572_294195/0"
        ]
    },
    {
        "time": "04-09 08:21",
        "title": "林书豪结束隔离后首次公开亮相 听听他怎么说",
        "link": "https://new.qq.com/sv1/qd/aoyou.html?cmsid=SPO2020040900306500",
        "images": [
            "https://inews.gtimg.com/newsapp_ls/0/11557695116_294195/0"
        ]
    },
    {
        "time": "04-09 08:42",
        "title": "F1真有完美车手存在吗？汉密尔顿舒马赫非要站队你选谁？",
        "link": "https://new.qq.com/sv1/qd/aoyou.html?cmsid=20200409A04CGX00",
        "images": [
            "https://inews.gtimg.com/newsapp_ls/0/11557755594_295195/0",
            "https://inews.gtimg.com/newsapp_ls/0/11557755595_295195/0",
            "https://inews.gtimg.com/newsapp_ls/0/11557755596_295195/0"
        ]
    },
    {
        "time": "04-09 09:44",
        "title": "趁你病要你命？英媒：德甲两豪门哄抢蓝军铁卫，这还让人玩么？",
        "link": "https://new.qq.com/sv1/qd/aoyou.html?cmsid=20200409A05X8500",
        "images": [
            "https://inews.gtimg.com/newsapp_ls/0/11557994895_295195/0",
            "https://inews.gtimg.com/newsapp_ls/0/11557994896_295195/0",
            "https://inews.gtimg.com/newsapp_ls/0/11557994897_295195/0"
        ]
    },
    {
        "time": "04-09 09:20",
        "title": "好消息！国足下半年将迎3大强援 中国队这11人首发给几分？",
        "link": "https://new.qq.com/sv1/qd/aoyou.html?cmsid=20200408A0SBQJ00",
        "images": [
            "https://inews.gtimg.com/newsapp_ls/0/11557941364_295195/0",
            "https://inews.gtimg.com/newsapp_ls/0/11557941365_295195/0",
            "https://inews.gtimg.com/newsapp_ls/0/11557941366_295195/0"
        ]
    },
    {
        "time": "04-09 09:31",
        "title": "前巴萨主帅力荐签回内马尔：他比劳塔罗更有优势！但巴萨逆境只能看梅西",
        "link": "https://new.qq.com/sv1/qd/aoyou.html?cmsid=20200409A05JFN00",
        "images": [
            "https://inews.gtimg.com/newsapp_ls/0/11557941155_294195/0"
        ]
    },
    {
        "time": "04-09 09:13",
        "title": "皇马降薪过程曝光！34岁队长带头劝说＋5大球星协调，5天达成统一",
        "link": "https://new.qq.com/sv1/qd/aoyou.html?cmsid=20200409A052A000",
        "images": [
            "https://inews.gtimg.com/newsapp_ls/0/11557866592_295195/0",
            "https://inews.gtimg.com/newsapp_ls/0/11557866593_295195/0",
            "https://inews.gtimg.com/newsapp_ls/0/11557866594_295195/0"
        ]
    },
    {
        "time": "04-09 09:41",
        "title": "致青春！罗纳尔多怒赞贝克汉姆：史上最佳之一，能进巴西队",
        "link": "https://new.qq.com/sv1/qd/aoyou.html?cmsid=20200409A05UEO00",
        "images": [
            "https://inews.gtimg.com/newsapp_ls/0/11557985589_295195/0",
            "https://inews.gtimg.com/newsapp_ls/0/11557985590_295195/0",
            "https://inews.gtimg.com/newsapp_ls/0/11557985591_295195/0"
        ]
    },
    {
        "time": "04-09 09:12",
        "title": "鲁能预备队多位球员结束隔离恢复训练，看看是否有你熟悉的面孔",
        "link": "https://new.qq.com/sv1/qd/aoyou.html?cmsid=20200409A0551700",
        "images": [
            "https://inews.gtimg.com/newsapp_ls/0/11557879925_295195/0",
            "https://inews.gtimg.com/newsapp_ls/0/11557879926_295195/0",
            "https://inews.gtimg.com/newsapp_ls/0/11557879927_295195/0"
        ]
    },
    {
        "time": "04-09 09:43",
        "title": "索帅坚称博格巴对曼联仍重要，与妖星并列！曝皇马希望9千万买他",
        "link": "https://new.qq.com/sv1/qd/aoyou.html?cmsid=20200409A05RHM00",
        "images": [
            "https://inews.gtimg.com/newsapp_ls/0/11557994846_295195/0",
            "https://inews.gtimg.com/newsapp_ls/0/11557994847_295195/0",
            "https://inews.gtimg.com/newsapp_ls/0/11557994848_295195/0"
        ]
    },
    {
        "time": "04-09 09:02",
        "title": "中国足协或今日出台2020赛季减薪令 中超球员还能赚几个钱？",
        "link": "https://new.qq.com/sv1/qd/aoyou.html?cmsid=20200409A04QGN00",
        "images": [
            "https://inews.gtimg.com/newsapp_ls/0/11557822237_295195/0",
            "https://inews.gtimg.com/newsapp_ls/0/11557822238_295195/0",
            "https://inews.gtimg.com/newsapp_ls/0/11557822239_295195/0"
        ]
    },
    {
        "time": "04-09 09:03",
        "title": "索帅称曼联要趁虚而入买人，遭炮轰无情！豪言英超重启后延续火热状态",
        "link": "https://new.qq.com/sv1/qd/aoyou.html?cmsid=20200409A04P9300",
        "images": [
            "https://inews.gtimg.com/newsapp_ls/0/11557826410_295195/0",
            "https://inews.gtimg.com/newsapp_ls/0/11557826411_295195/0",
            "https://inews.gtimg.com/newsapp_ls/0/11557826412_295195/0"
        ]
    },
    {
        "time": "04-09 09:53",
        "title": "暴揍菜鸟，逼队友退役，铁血硬汉加内特的另一面人生",
        "link": "https://new.qq.com/sv1/qd/aoyou.html?cmsid=20200409A0678Y00",
        "images": [
            "https://inews.gtimg.com/newsapp_ls/0/11558070170_295195/0",
            "https://inews.gtimg.com/newsapp_ls/0/11558070171_295195/0",
            "https://inews.gtimg.com/newsapp_ls/0/11558070172_295195/0"
        ]
    },
    {
        "time": "04-09 09:09",
        "title": "猛龙前锋回应隔离期间买生活用品被发现：希望世界回到原来的样子",
        "link": "https://new.qq.com/sv1/qd/aoyou.html?cmsid=20200409A04YEL00",
        "images": [
            "https://inews.gtimg.com/newsapp_ls/0/11557851869_294195/0"
        ]
    },
    {
        "time": "04-09 09:20",
        "title": "天海为何还没中超资格？足球报揭秘：万通控股的2.5亿还没到账",
        "link": "https://new.qq.com/sv1/qd/aoyou.html?cmsid=20200409A0589Y00",
        "images": [
            "https://inews.gtimg.com/newsapp_ls/0/11557892866_295195/0",
            "https://inews.gtimg.com/newsapp_ls/0/11557892867_295195/0",
            "https://inews.gtimg.com/newsapp_ls/0/11557892868_295195/0"
        ]
    },
    {
        "time": "04-09 09:55",
        "title": "詹皇随时准备赛季恢复！为争冠训练不松懈 对手感慨：这就是差距",
        "link": "https://new.qq.com/sv1/qd/aoyou.html?cmsid=20200409A04UFY00",
        "images": [
            "https://inews.gtimg.com/newsapp_ls/0/11558043800_295195/0",
            "https://inews.gtimg.com/newsapp_ls/0/11558043801_295195/0",
            "https://inews.gtimg.com/newsapp_ls/0/11558043802_295195/0"
        ]
    },
    {
        "time": "04-09 09:40",
        "title": "错过今年老詹湖人生涯将无冠？老詹的答复很直接，他并不担忧",
        "link": "https://new.qq.com/sv1/qd/aoyou.html?cmsid=20200409A05T9S00",
        "images": [
            "https://inews.gtimg.com/newsapp_ls/0/11557980565_295195/0",
            "https://inews.gtimg.com/newsapp_ls/0/11557980566_295195/0",
            "https://inews.gtimg.com/newsapp_ls/0/11557980567_295195/0"
        ]
    },
    {
        "time": "04-09 09:03",
        "title": "埃利奥特不会就此放弃，他们将努力带米兰重回巅峰",
        "link": "https://new.qq.com/sv1/qd/aoyou.html?cmsid=20200409A050B200",
        "images": [
            "https://inews.gtimg.com/newsapp_ls/0/11557861615_294195/0"
        ]
    },
    {
        "time": "04-09 07:48",
        "title": "恒大韦世豪庆生照曝光：生日帽尖刀手标志性笑容，吃榴莲千层蛋糕",
        "link": "https://new.qq.com/sv1/qd/aoyou.html?cmsid=20200409A03L3S00",
        "images": [
            "https://inews.gtimg.com/newsapp_ls/0/11557613828_294195/0"
        ]
    },
    {
        "time": "04-09 07:22",
        "title": "世界第一拳击推广人：白大拿刻薄成性近乎违法，UFC无法比肩拳击",
        "link": "https://new.qq.com/sv1/qd/aoyou.html?cmsid=20200408A0UIBZ00",
        "images": [
            "https://inews.gtimg.com/newsapp_ls/0/11556886912_295195/0",
            "https://inews.gtimg.com/newsapp_ls/0/11556886913_295195/0",
            "https://inews.gtimg.com/newsapp_ls/0/11556886914_295195/0"
        ]
    },
    {
        "time": "04-09 05:16",
        "title": "美媒重排03年选秀顺位！韦德成为榜眼，帕楚里亚上升了32个顺位",
        "link": "https://new.qq.com/sv1/qd/aoyou.html?cmsid=20200408A0TC7G00",
        "images": [
            "https://inews.gtimg.com/newsapp_ls/0/11557386971_295195/0",
            "https://inews.gtimg.com/newsapp_ls/0/11557386972_295195/0",
            "https://inews.gtimg.com/newsapp_ls/0/11557386974_295195/0"
        ]
    },
    {
        "time": "04-09 07:41",
        "title": "35岁霸气依旧！詹姆斯赛季超暴力扣篮集锦",
        "link": "https://new.qq.com/sv1/qd/aoyou.html?cmsid=SPO2020040900221900",
        "images": [
            "https://inews.gtimg.com/newsapp_ls/0/11557600993_294195/0"
        ]
    },
    {
        "time": "04-09 07:44",
        "title": "法拉利与红牛的维修区之争 输赢就在分秒之间",
        "link": "https://new.qq.com/sv1/qd/aoyou.html?cmsid=SPO2020040900226300",
        "images": [
            "https://inews.gtimg.com/newsapp_ls/0/11557604136_294195/0"
        ]
    },
    {
        "time": "04-09 07:42",
        "title": "全面比较东艾西科南麦北卡 科比的进攻效率高不高",
        "link": "https://new.qq.com/sv1/qd/aoyou.html?cmsid=20200408A0UAQJ00",
        "images": [
            "https://inews.gtimg.com/newsapp_ls/0/11557607593_295195/0",
            "https://inews.gtimg.com/newsapp_ls/0/11557607594_295195/0",
            "https://inews.gtimg.com/newsapp_ls/0/11557607595_295195/0"
        ]
    },
    {
        "time": "04-09 08:51",
        "title": "完美诠释“百步穿杨” 张堃鹏2017大师赛西宁站霸气夺冠",
        "link": "https://new.qq.com/sv1/qd/aoyou.html?cmsid=20200409A04J6200",
        "images": [
            "https://inews.gtimg.com/newsapp_ls/0/11557788492_294195/0"
        ]
    },
    {
        "time": "04-09 08:43",
        "title": "拜仁后防线大重组！内部挖潜看似完美，其实还准备买两个边后卫",
        "link": "https://new.qq.com/sv1/qd/aoyou.html?cmsid=20200409A04E5Z00",
        "images": [
            "https://inews.gtimg.com/newsapp_ls/0/11557762205_295195/0",
            "https://inews.gtimg.com/newsapp_ls/0/11557762206_295195/0",
            "https://inews.gtimg.com/newsapp_ls/0/11557762207_295195/0"
        ]
    },
    {
        "time": "04-09 08:28",
        "title": "詹皇自曝一周要进行至少四次训练 还常带着儿子去蹭别人家球馆训练",
        "link": "https://new.qq.com/sv1/qd/aoyou.html?cmsid=20200409A044B700",
        "images": [
            "https://inews.gtimg.com/newsapp_ls/0/11557713244_294195/0",
            "https://inews.gtimg.com/newsapp_ls/0/11557713258_294195/0",
            "https://inews.gtimg.com/newsapp_ls/0/11557713261_294195/0"
        ]
    },
    {
        "time": "04-09 08:09",
        "title": "女排21岁扣高3米27天才上线！曾获郎平栽培，袁心玥最佳替身？",
        "link": "https://new.qq.com/sv1/qd/aoyou.html?cmsid=20200409A03V9I00",
        "images": [
            "https://inews.gtimg.com/newsapp_ls/0/11557660243_294195/0",
            "https://inews.gtimg.com/newsapp_ls/0/11557660242_294195/0",
            "https://inews.gtimg.com/newsapp_ls/0/11557660244_294195/0"
        ]
    },
    {
        "time": "04-09 08:21",
        "title": "佩林卡：湖人众将线上视频合练 曼巴精神助我们渡过难关",
        "link": "https://new.qq.com/sv1/qd/aoyou.html?cmsid=20200409A040XV00",
        "images": [
            "https://inews.gtimg.com/newsapp_ls/0/11557719424_294195/0"
        ]
    },
    {
        "time": "04-09 08:15",
        "title": "中国足协下发国际足联疫情期间最新文件，文件都讲了什么？",
        "link": "https://new.qq.com/sv1/qd/aoyou.html?cmsid=20200409A03YB400",
        "images": [
            "https://inews.gtimg.com/newsapp_ls/0/11557684412_294195/0"
        ]
    },
    {
        "time": "04-09 06:20",
        "title": "太无聊？丁威迪称要竞聘公牛总经理 签浓眉哥组四巨头",
        "link": "https://new.qq.com/sv1/qd/aoyou.html?cmsid=20200409A02P2M00",
        "images": [
            "https://inews.gtimg.com/newsapp_ls/0/11557454726_294195/0"
        ]
    },
    {
        "time": "04-09 07:32",
        "title": "万幸！罗本亲承妻子感染新冠但已康复 他本人和孩子检测呈阴性",
        "link": "https://new.qq.com/sv1/qd/aoyou.html?cmsid=20200409A03F1A00",
        "images": [
            "https://inews.gtimg.com/newsapp_ls/0/11557578769_294195/0"
        ]
    },
    {
        "time": "04-09 06:26",
        "title": "罗本：我的妻子感染了新冠病毒，目前已康复，我和孩子并未感染",
        "link": "https://new.qq.com/sv1/qd/aoyou.html?cmsid=20200409A02QGT00",
        "images": [
            "https://inews.gtimg.com/newsapp_ls/0/11557463496_294195/0"
        ]
    },
    {
        "time": "04-09 06:17",
        "title": "武僧一龙遭警告！刘信达宿敌：你再不加强锻炼，金钟罩就失灵了",
        "link": "https://new.qq.com/sv1/qd/aoyou.html?cmsid=20200408A0K1HB00",
        "images": [
            "https://inews.gtimg.com/newsapp_ls/0/11557617117_295195/0",
            "https://inews.gtimg.com/newsapp_ls/0/11557617118_295195/0",
            "https://inews.gtimg.com/newsapp_ls/0/11557617120_295195/0"
        ]
    },
    {
        "time": "04-09 07:45",
        "title": "要想让格罗斯让让你，首先你得是个狠人！",
        "link": "https://new.qq.com/sv1/qd/aoyou.html?cmsid=SPO2020040900227200",
        "images": [
            "https://inews.gtimg.com/newsapp_ls/0/11557605997_294195/0"
        ]
    },
    {
        "time": "04-09 07:32",
        "title": "旧将：国米可以签下梅西，张康阳有财力和野心",
        "link": "https://new.qq.com/sv1/qd/aoyou.html?cmsid=20200409A03EVY00",
        "images": [
            "https://inews.gtimg.com/newsapp_ls/0/11557578344_294195/0"
        ]
    },
    {
        "time": "04-09 07:50",
        "title": "新科冠军WWE天之骄子德鲁：得亏当年我没夺冠 否则没有如今的我",
        "link": "https://new.qq.com/sv1/qd/aoyou.html?cmsid=20200408A0R49500",
        "images": [
            "https://inews.gtimg.com/newsapp_ls/0/11557632052_294195/0"
        ]
    },
    {
        "time": "04-09 07:57",
        "title": "德转进行特别身价更新，球员总身价蒸发92亿欧",
        "link": "https://new.qq.com/sv1/qd/aoyou.html?cmsid=20200409A03OHL00",
        "images": [
            "https://inews.gtimg.com/newsapp_ls/0/11557632588_294195/0"
        ]
    },
    {
        "time": "04-09 07:48",
        "title": "西甲豪门又官宣1噩耗 81岁传奇前锋去世 11天4人死亡最小仅14岁",
        "link": "https://new.qq.com/sv1/qd/aoyou.html?cmsid=20200409A03L4X00",
        "images": [
            "https://inews.gtimg.com/newsapp_ls/0/11557615408_295195/0",
            "https://inews.gtimg.com/newsapp_ls/0/11557615409_295195/0",
            "https://inews.gtimg.com/newsapp_ls/0/11557615410_295195/0"
        ]
    },
    {
        "time": "04-09 08:37",
        "title": "CBA历史最佳搭档评选揭幕战：姚明刘炜轻取胡唐组合晋级",
        "link": "https://new.qq.com/sv1/qd/aoyou.html?cmsid=20200408A0Q8F700",
        "images": [
            "https://inews.gtimg.com/newsapp_ls/0/11557740410_294195/0",
            "https://inews.gtimg.com/newsapp_ls/0/11557740401_294195/0",
            "https://inews.gtimg.com/newsapp_ls/0/11557740426_294195/0"
        ]
    },
    {
        "time": "04-09 08:48",
        "title": "王鹏演绎什么叫100％开球清台率",
        "link": "https://new.qq.com/sv1/qd/aoyou.html?cmsid=20200409A04GX900",
        "images": [
            "https://inews.gtimg.com/newsapp_ls/0/11557787622_294195/0"
        ]
    },
    {
        "time": "04-09 08:35",
        "title": "国足对伊朗最狡猾的胜利！邵佳一“控制”了裁判，门将献神扑",
        "link": "https://new.qq.com/sv1/qd/aoyou.html?cmsid=20200409A0492X00",
        "images": [
            "https://inews.gtimg.com/newsapp_ls/0/11557739463_295195/0",
            "https://inews.gtimg.com/newsapp_ls/0/11557739464_295195/0",
            "https://inews.gtimg.com/newsapp_ls/0/11557739465_295195/0"
        ]
    },
    {
        "time": "04-09 08:26",
        "title": "经典回忆杀：中国足球职业化最高光时刻！穆里奇助攻艾克森封王",
        "link": "https://new.qq.com/sv1/qd/aoyou.html?cmsid=20200408V0UFMD00",
        "images": [
            "https://inews.gtimg.com/newsapp_ls/0/11557719279_294195/0"
        ]
    },
    {
        "time": "04-09 08:52",
        "title": "FIFA已同意为中国联赛增设转会窗，确定开赛时间后申请即可",
        "link": "https://new.qq.com/sv1/qd/aoyou.html?cmsid=20200409A04JKQ00",
        "images": [
            "https://inews.gtimg.com/newsapp_ls/0/11557784398_294195/0",
            "https://inews.gtimg.com/newsapp_ls/0/11557784406_294195/0",
            "https://inews.gtimg.com/newsapp_ls/0/11557784412_294195/0"
        ]
    },
    {
        "time": "04-09 08:45",
        "title": "皇马官宣降薪10％或20％ 两种方案应对危机 却遭德国球星抵制",
        "link": "https://new.qq.com/sv1/qd/aoyou.html?cmsid=20200409A04F8900",
        "images": [
            "https://inews.gtimg.com/newsapp_ls/0/11557767412_294195/0"
        ]
    },
    {
        "time": "04-09 08:39",
        "title": "伊卡尔迪铁心回归意甲联赛，也不排除留在国际米兰的可能性？",
        "link": "https://new.qq.com/sv1/qd/aoyou.html?cmsid=20200409A04BJW00",
        "images": [
            "https://inews.gtimg.com/newsapp_ls/0/11557749963_295195/0",
            "https://inews.gtimg.com/newsapp_ls/0/11557749964_295195/0",
            "https://inews.gtimg.com/newsapp_ls/0/11557749965_295195/0"
        ]
    },
    {
        "time": "04-09 08:56",
        "title": "噩耗！马竞传奇离世，感染新冠＋与癌症斗争，俱乐部降半旗默哀",
        "link": "https://new.qq.com/sv1/qd/aoyou.html?cmsid=20200409A04M3F00",
        "images": [
            "https://inews.gtimg.com/newsapp_ls/0/11557801870_295195/0",
            "https://inews.gtimg.com/newsapp_ls/0/11557801871_295195/0",
            "https://inews.gtimg.com/newsapp_ls/0/11557801872_295195/0"
        ]
    },
    {
        "time": "04-09 08:39",
        "title": "历史上的今天：奥拉朱旺空砍43分13板8断5帽",
        "link": "https://new.qq.com/sv1/qd/aoyou.html?cmsid=20200409A04EPX00",
        "images": [
            "https://inews.gtimg.com/newsapp_ls/0/11557765770_294195/0"
        ]
    },
    {
        "time": "04-09 08:23",
        "title": "克雷斯波：C罗职业生涯很长青，但大罗是无法企及的存在",
        "link": "https://new.qq.com/sv1/qd/aoyou.html?cmsid=20200409A04BRZ00",
        "images": [
            "https://inews.gtimg.com/newsapp_ls/0/11557753591_294195/0"
        ]
    },
    {
        "time": "04-09 08:43",
        "title": "皇马宣布降薪决定！最多可省1亿欧元，30岁巨星1天前还在坚决反对",
        "link": "https://new.qq.com/sv1/qd/aoyou.html?cmsid=20200409A04E4C00",
        "images": [
            "https://inews.gtimg.com/newsapp_ls/0/11557758230_294195/0",
            "https://inews.gtimg.com/newsapp_ls/0/11557758235_294195/0",
            "https://inews.gtimg.com/newsapp_ls/0/11557758228_294195/0"
        ]
    },
    {
        "time": "04-09 08:48",
        "title": "西卡笑笑大赞iG选人眼光：就是因为Kid推荐了Theshy",
        "link": "https://new.qq.com/sv1/qd/aoyou.html?cmsid=20200409A04H7Y00",
        "images": [
            "https://inews.gtimg.com/newsapp_ls/0/11557778602_295195/0",
            "https://inews.gtimg.com/newsapp_ls/0/11557778603_295195/0",
            "https://inews.gtimg.com/newsapp_ls/0/11557778604_295195/0"
        ]
    },
    {
        "time": "04-09 06:38",
        "title": "TheShy虎牙首播人气破2000万：被霸哥单杀只是付之一笑",
        "link": "https://new.qq.com/sv1/qd/aoyou.html?cmsid=20200409A02W3500",
        "images": [
            "https://inews.gtimg.com/newsapp_ls/0/11557482217_294195/0"
        ]
    },
    {
        "time": "04-09 06:52",
        "title": "斯诺克世锦赛若今夏举行谁是夺冠热门？罗伯逊：看好奥沙利文",
        "link": "https://new.qq.com/sv1/qd/aoyou.html?cmsid=20200409A02ZRJ00",
        "images": [
            "https://inews.gtimg.com/newsapp_ls/0/11557602026_294195/0"
        ]
    },
    {
        "time": "04-09 06:00",
        "title": "美翻天！耐克用心设计新球衣，中超列强秒变F4",
        "link": "https://new.qq.com/sv1/qd/aoyou.html?cmsid=20200408A0TMQ500",
        "images": [
            "https://inews.gtimg.com/newsapp_ls/0/11557419186_295195/0",
            "https://inews.gtimg.com/newsapp_ls/0/11557419187_295195/0",
            "https://inews.gtimg.com/newsapp_ls/0/11557419188_295195/0"
        ]
    },
    {
        "time": "04-09 07:35",
        "title": "惊呆！西班牙花滑美男宅家炫技 陆地上演高难度旋转",
        "link": "https://new.qq.com/sv1/qd/aoyou.html?cmsid=SPO2020040900204100",
        "images": [
            "https://inews.gtimg.com/newsapp_ls/0/11557581178_294195/0"
        ]
    },
    {
        "time": "04-09 07:48",
        "title": "兵不厌诈！看大曼宁如何用欺诈战术完美演绎精妙战术与团队配合！",
        "link": "https://new.qq.com/sv1/qd/aoyou.html?cmsid=SPO2020040900231800",
        "images": [
            "https://inews.gtimg.com/newsapp_ls/0/11557613357_294195/0"
        ]
    },
    {
        "time": "04-09 07:20",
        "title": "马奎兹最霸气的一场比赛！直接打晕帕奎奥夺走金腰带",
        "link": "https://new.qq.com/sv1/qd/aoyou.html?cmsid=SPO2020040900171700",
        "images": [
            "https://inews.gtimg.com/newsapp_ls/0/11557549554_294195/0"
        ]
    },
    {
        "time": "04-09 07:21",
        "title": "中国搏击专家盛赞国外格斗赛事，该赛事却办一件错事被UFC取代",
        "link": "https://new.qq.com/sv1/qd/aoyou.html?cmsid=20200408A0I27C00",
        "images": [
            "https://inews.gtimg.com/newsapp_ls/0/11557470341_295195/0",
            "https://inews.gtimg.com/newsapp_ls/0/11557470342_295195/0",
            "https://inews.gtimg.com/newsapp_ls/0/11557470343_295195/0"
        ]
    },
    {
        "time": "04-09 07:12",
        "title": "天津日报：王霜与女足会合后得先隔离 仅剩1周合练，从体能做起",
        "link": "https://new.qq.com/sv1/qd/aoyou.html?cmsid=SPO2020040900155700",
        "images": [
            "https://inews.gtimg.com/newsapp_ls/0/11557539701_294195/0"
        ]
    }
]